setup.py
dwytsongs/__init__.py
dwytsongs/exceptions.py
dwytsongs/utils.py
dwytsongs.egg-info/PKG-INFO
dwytsongs.egg-info/SOURCES.txt
dwytsongs.egg-info/dependency_links.txt
dwytsongs.egg-info/requires.txt
dwytsongs.egg-info/top_level.txt