Metadata-Version: 1.0
Name: dwytsongs
Version: 2.5.1
Summary: Downloads songs, albums or playlists through spotify or deezer link from youtube
Home-page: https://github.com/An0nimia/dwytsongs
Author: An0nimia
Author-email: An0nimia@protonmail.com
License: CC BY-NC-SA 4.0
Platform: UNKNOWN
